xfps/__init__.py
xfps/effects.py
xfps/particle_system.py
xfps/__pycache__/__init__.cpython-311.pyc
xfps/__pycache__/effects.cpython-311.pyc
xfps/__pycache__/particle_system.cpython-311.pyc
xfps-0.1.9.dist-info/LICENSE
xfps-0.1.9.dist-info/METADATA
xfps-0.1.9.dist-info/WHEEL
xfps-0.1.9.dist-info/top_level.txt
xfps-0.1.9.dist-info/RECORD
