Metadata-Version: 2.1
Name: xfps
Version: 0.1.9
Summary: A particle system and effects library for Pygame
Home-page: https://github.com/XFajk/xfps/tree/main
Author: XFajk
Author-email: ertyperty24@gmail.com
Classifier: Development Status :: 3 - Alpha
Classifier: Intended Audience :: Developers
Classifier: License :: OSI Approved :: MIT License
Classifier: Programming Language :: Python :: 3.11
License-File: LICENSE
Requires-Dist: pygame-ce
